packtivity/.gitignore
packtivity/__init__.py
packtivity/asyncbackends.py
packtivity/backendutils.py
packtivity/cli.py
packtivity/datamodel.py
packtivity/logutils.py
packtivity/plugins.py
packtivity/syncbackends.py
packtivity/typedleafs.py
packtivity/utils.py
packtivity/datamodels/__init__.py
packtivity/datamodels/purejson.py
packtivity/handlers/__init__.py
packtivity/handlers/environment_handlers.py
packtivity/handlers/execution_handlers.py
packtivity/handlers/process_handlers.py
packtivity/handlers/publisher_handlers.py
packtivity/kubernetes/__init__.py
packtivity/kubernetes/jobspec.py
packtivity/kubernetes/kubedirectjobbackend.py
packtivity/kubernetes/kubekrbmixin.py
packtivity/kubernetes/kubespecmixin.py
packtivity/kubernetes/kubesubmitmixin.py
packtivity/statecontexts/__init__.py
packtivity/statecontexts/posixfs_context.py
packtivity-0.17.0.dist-info/LICENSE
packtivity-0.17.0.dist-info/METADATA
packtivity-0.17.0.dist-info/WHEEL
packtivity-0.17.0.dist-info/entry_points.txt
packtivity-0.17.0.dist-info/top_level.txt
packtivity-0.17.0.dist-info/RECORD
