Metadata-Version: 2.1
Name: packtivity
Version: 0.17.0
Summary: packtivity - general purpose schema + bindings for PROV activities
Home-page: https://github.com/yadage/packtivity
Author: Lukas Heinrich, Matthew Feickert
Author-email: lukas.heinrich@gmail.com, matthew.feickert@cern.ch
License: MIT
Classifier: Development Status :: 4 - Beta
Classifier: Intended Audience :: Science/Research
Classifier: License :: OSI Approved :: MIT License
Classifier: Programming Language :: Python :: 3
Classifier: Programming Language :: Python :: 3 :: Only
Classifier: Programming Language :: Python :: 3.8
Classifier: Programming Language :: Python :: 3.9
Classifier: Programming Language :: Python :: 3.10
Classifier: Programming Language :: Python :: 3.11
Classifier: Programming Language :: Python :: 3.12
Classifier: Programming Language :: Python :: Implementation :: CPython
Classifier: Topic :: Scientific/Engineering
Classifier: Topic :: Scientific/Engineering :: Physics
Classifier: Operating System :: OS Independent
Requires-Python: >=3.8
License-File: LICENSE
Requires-Dist: requests[security]
Requires-Dist: jsonschema
Requires-Dist: jsonref
Requires-Dist: pyyaml
Requires-Dist: click
Requires-Dist: glob2
Requires-Dist: jsonpointer
Requires-Dist: jsonpath-rw
Requires-Dist: jq >=1.0.0
Requires-Dist: yadage-schemas
Requires-Dist: mock
Requires-Dist: dirhash >=0.4.0
Provides-Extra: celery
Requires-Dist: celery >=5.0.0 ; extra == 'celery'
Requires-Dist: redis ; extra == 'celery'
